loggpy/__init__.py
loggpy-0.1.0.dist-info/LICENSE
loggpy-0.1.0.dist-info/METADATA
loggpy-0.1.0.dist-info/WHEEL
loggpy-0.1.0.dist-info/top_level.txt
loggpy-0.1.0.dist-info/RECORD
