Metadata-Version: 2.1
Name: loggpy
Version: 0.1.0
Summary: A powerful Python logging library with custom levels and colored output support
Home-page: https://github.com/ReiDoBrega/loggpy
Author: ReiDoBrega
Author-email: pedro94782079@gmail.com
License: MIT
Project-URL: Homepage, https://github.com/ReiDoBrega/loggpy
Project-URL: Repository, https://github.com/ReiDoBrega/loggpy
Project-URL: Bug Tracker, https://github.com/ReiDoBrega/loggpy/issues
Keywords: logging,logger,colored-logs,custom-logging,terminal,debug,development-tools,logging-library
Classifier: Development Status :: 4 - Beta
Classifier: Intended Audience :: Developers
Classifier: Programming Language :: Python :: 3
Classifier: Programming Language :: Python :: 3.7
Classifier: Programming Language :: Python :: 3.8
Classifier: Programming Language :: Python :: 3.9
Classifier: Programming Language :: Python :: 3.10
Classifier: Programming Language :: Python :: 3.11
Classifier: License :: OSI Approved :: MIT License
Classifier: Operating System :: OS Independent
Classifier: Topic :: Software Development :: Libraries :: Python Modules
Classifier: Topic :: System :: Logging
Requires-Python: >=3.7
License-File: LICENSE
Requires-Dist: coloredlogs>=15.0.0
